{
  "Altayçeşme": [
    "Çeşme Sokak",
    "Maltepe Caddesi",
    "Maltepe Sokak"
  ],
  "Altıntepe": [
    "Altın Sokak",
    "Tepe Sokak",
    "Altıntepe Sokak",
    "Maltepe Caddesi",
    "Maltepe Sokak"
  ],
  "Aydınevler": [
    "Aydın Caddesi",
    "Aydın Sokak",
    "Maltepe Caddesi",
    "Maltepe Sokak"
  ],
  "Bağlarbaşı": [
    "Bağlarbaşı Caddesi",
    "Bağlarbaşı Sokak",
    "İstanbul Sokak",
    "Maltepe Caddesi",
    "Maltepe Sokak"
  ],
  "Başıbüyük": [
    "Başıbüyük Yolu",
    "Başıbüyük Caddesi"
  ],
  "Büyükbakkalköy": [
    "Büyükbakkalköy Yolu",
    "Büyükbakkalköy Caddesi"
  ],
  "Cevizli": [
    "Cevizli Sokak",
    "Maltepe Caddesi",
    "Maltepe Sokak",
    "İstanbul Sokak"
  ],
  "Çınar": [
    "Çınar Caddesi"
  ],
  "Esenkent": [
    "Özmen Sokak Yanyolu",
    "Esen Sokak",
    "Maltepe Caddesi",
    "Maltepe Sokak",
    "Kent Sokak",
    "Esen Caddesi"
  ],
  "Feyzullah": [
    "Feyzullah Caddesi",
    "Feyzullah Sokak",
    "Maltepe Caddesi",
    "Maltepe Sokak"
  ],
  "Fındıklı": [
    "Fındıklı Sokak",
    "Fındıklık Sokak",
    "Maltepe Caddesi",
    "Maltepe Sokak",
    "Türkiye Caddesi"
  ],
  "Girne": [
    "Girne Sokağı",
    "Girne Caddesi",
    "Girne Cd.",
    "Maltepe Caddesi",
    "Maltepe Sokak",
    "Girne Sokak",
    "1. Girne Sokak",
    "3. Girne Sokak"
  ],
  "Gülsuyu": [
    "Gül Caddesi",
    "Gül Sokak",
    "Gülsuyu Sokak",
    "Maltepe Caddesi",
    "Maltepe Sokak",
    "1. Gül Sokak",
    "Gül 2. Sokak"
  ],
  "Gülensu": [
    "Gülensu Sokak",
    "Maltepe Caddesi",
    "Maltepe Sokak",
    "Türkiye Caddesi"
  ],
  "İdealtepe": [
    "İdealtepe Yolu",
    "Maltepe Caddesi"
  ],
  "Küçükyalı": [
    "Küçükyalı Caddesi",
    "Küçük Sokak",
    "Küçük Yalı Sokak",
    "Küçükyalı Sokak"
  ],
  "Yalı": [
    "Yalı Mah.",
    "Yali - Esenyurdum Çıkmazı",
    "Maltepe Caddesi",
    "Maltepe Sokak",
    "Yalı Sokak",
    "Yalı Caddesi",
    "Yalı 3. Sokak",
    "Yalı 1. Sokak",
    "Yalı 2. Sokak"
  ],
  "Zümrütevler": [
    "Zümrütler Kavşağı",
    "Zümrüt Sokak",
    "Zümrüt Evler Sokak",
    "Zümrüt Caddesi",
    "Zümrüt Çıkmazı",
    "1. Zümrüt Sokak",
    "2. Zümrüt Sokak",
    "Zümrüt 2. Sokak",
    "Zümrüt 5. Sokak",
    "Zümrüt 4. Sokak",
    "Zümrüt 1. Sokak",
    "Maltepe Caddesi",
    "Maltepe Sokak"
  ]
}